ai4love_tools/__init__.py
ai4love_tools/tenant/__init__.py
ai4love_tools/tenant/context.py
ai4love_tools/tenant/decorators.py
ai4love_tools/tenant/exceptions.py
ai4love_tools/tenant/extractor.py
ai4love_tools/tenant/sql.py
ai4love_tools/tenant/sqlalchemy_integration.py
ai4love_tools-0.0.9.dist-info/METADATA
ai4love_tools-0.0.9.dist-info/WHEEL
ai4love_tools-0.0.9.dist-info/top_level.txt
ai4love_tools-0.0.9.dist-info/RECORD
